{"lastUsed":1622582978098,"path":"C:\/workspaces\/ws-bootcamp\/testeJUnit","projectCount":1,"recentFiles":[{"path":"\/teste-junit\/src\/entities","parentWorkspace":"C:\/workspaces\/ws-bootcamp\/testeJUnit","name":"Account.java","lastModified":1622582989368,"locationURI":"file:\/C:\/workspaces\/ws-bootcamp\/testeJUnit\/teste-junit\/src\/entities\/Account.java"},{"path":"\/teste-junit\/src\/tests\/entities","parentWorkspace":"C:\/workspaces\/ws-bootcamp\/testeJUnit","name":"AccountTests.java","lastModified":1622582978098,"locationURI":"file:\/C:\/workspaces\/ws-bootcamp\/testeJUnit\/teste-junit\/src\/tests\/entities\/AccountTests.java"}]}